employment_hero_sdk/__init__.py
employment_hero_sdk/__version__.py
employment_hero_sdk/api/__init__.py
employment_hero_sdk/api/base.py
employment_hero_sdk/api/business.py
employment_hero_sdk/api/employee.py
employment_hero_sdk/api/location.py
employment_hero_sdk/api/report.py
employment_hero_sdk/client.py
employment_hero_sdk/exceptions.py
employment_hero_sdk/models.py
employment_hero_sdk/utils.py
employment_hero_sdk-0.1.5.dist-info/METADATA
employment_hero_sdk-0.1.5.dist-info/WHEEL
employment_hero_sdk-0.1.5.dist-info/RECORD
