Metadata-Version: 2.1
Name: employment-hero-sdk
Version: 0.1.5
Summary: Efficiently interact with the Employment Hero/Key Pay API
License: CC BY-NC 4.0
Author: duneraccoon
Author-email: benjamincsherro@hotmail.com
Requires-Python: >=3.10,<4.0
Classifier: License :: Other/Proprietary License
Classifier: Programming Language :: Python :: 3
Classifier: Programming Language :: Python :: 3.10
Classifier: Programming Language :: Python :: 3.11
Classifier: Programming Language :: Python :: 3.12
Requires-Dist: httpx (==0.28.1)
Requires-Dist: leaky-bucket-py (>=0.1.3,<0.2.0)
Requires-Dist: pandas (>=2.2.3,<3.0.0)
Requires-Dist: pydantic (==2.10.4)
Requires-Dist: redis (>=5.2.1,<6.0.0)
